{"data":[{"word":"Hulk Passed Away","group_id":"5670434718308776336","word_type":"2"},{"word":"Thomas And Kristen Pt 2 Update","group_id":"2002365046992393878","word_type":"2"},{"word":"Part 3 David Catherine Date Update","group_id":"9200812135539015345","word_type":"2"},{"word":"Gnarly Sophia","group_id":"208754507396278534"},{"word":"Creator Sight Insights","group_id":"7384495827173176434"},{"word":"Kou Mabuchi","group_id":"9167192387511792748"},{"word":"Gnarly Dance","group_id":"8476313821031893944"},{"word":"Barcelona Team Arrives At Stadium","group_id":"6684962462959931018"},{"word":"Sommer Own Goal","group_id":"1285550031322409518"},{"word":"decision day","group_id":"9175177554421256796"}],"status_code":0,"status_msg":"","log_id":"2025050116283232FCE3E5955F84285F00"}