{"data":[{"word":"TikTok Dances 2025","group_id":"7997607359311414522","word_type":"2"},{"word":"squirrel girl in marvel rivals","group_id":"6949128399496388840","word_type":"2"},{"word":"Lip Sync Song Trend","group_id":"1695114380957673414","word_type":"2"},{"word":"Beyonce In Atlanta","group_id":"184988625254452269"},{"word":"jandels new post","group_id":"7268116577733267245"},{"word":"Streak Reminder Trend","group_id":"6577957308097745316"},{"word":"Sounds To Lip Sync","group_id":"3359099431490862875"},{"word":"Milky Milk Milky Milk Trend","group_id":"6887830598083143753"},{"word":"Food Mukbangs","group_id":"150793515812860461"},{"word":"Buckle Bunny King Kitty","group_id":"3478138653021894827"}],"status_code":0,"status_msg":"","log_id":"20250711152629C9F874098624704C1D97"}