{"data":[{"word":"Wonder Movie Best Scenes","group_id":"4831079635455683576"},{"word":"Lady Gaga Starts Mayhem Ball Tour In Vegas","group_id":"4116089100193704230","word_type":"2"},{"word":"TikTok Dance Trend 2025","group_id":"1212861775715471946","word_type":"2"},{"word":"Huda On Call Her Daddy Tonight","group_id":"4875586170162726588","word_type":"2"},{"word":"Mukbangs Food","group_id":"2085021742158543003"},{"word":"‘The Summer I Turned Pretty’ Season 3","group_id":"3420676428504699029"},{"word":"Latina Girl Effect Trend","group_id":"7856334687827331710"},{"word":"Wing Stop Mukbangs","group_id":"314764955866401472"},{"word":"Buckle Bunny King Kitty","group_id":"3478138653021894827"},{"word":"7 Minutes In Heaven Animation","group_id":"2792394341384760040"}],"status_code":0,"status_msg":"","log_id":"2025071705282424ACD572B7F46A02EBD0"}