{"data":[{"word":"Traveling Ban In USA","group_id":"7196509808482951150","word_type":"2"},{"word":"tanner passed away","group_id":"2995790983990313104","word_type":"2"},{"word":"tiktok dance trend 2025","group_id":"1231913886315081090","word_type":"2"},{"word":"Diddy Verdict","group_id":"7445296880380789501"},{"word":"Devin Booker Trade","group_id":"8193368687416108455"},{"word":"low rise bush outfit trend","group_id":"8149846867889870768"},{"word":"Billie Eilish Edits","group_id":"4124003935993392219"},{"word":"Pink Starburst","group_id":"3889179475473049978"},{"word":"kissing strangers animation trend","group_id":"721000043123421103"},{"word":"camille shake it to the max","group_id":"144384484499557453"}],"status_code":0,"status_msg":"","log_id":"2025062616300517E14D5AAC090D1402CF"}