{"data":[{"word":"The Walking Dead Bloopers","group_id":"972832647468369481"},{"word":"Dance Trends On TikTok","group_id":"5670737950725724506","word_type":"2"},{"word":"Minecraft Ideas","group_id":"3655333852768919885"},{"word":"Aaron The Plumber Mom At Party","group_id":"7850020245668234422","word_type":"2"},{"word":"What Happened To Jack Doherty And Mckinley","group_id":"7573421296832838706","word_type":"2"},{"word":"Skims Tryon Review","group_id":"7164099536006789989"},{"word":"8 Key Changes For The New iPhone 17 Pro","group_id":"1502170078456146322"},{"word":"Styling Skims White Dress","group_id":"8892536666971524343"},{"word":"Lululemon Girls","group_id":"7929201488978904404"},{"word":"original video of bride singing","group_id":"9103292456684118093"}],"status_code":0,"status_msg":"","log_id":"202504072221012841D29CD485E9351C6F"}