{"data":[{"word":"Skims Review","group_id":"4241592612461751271"},{"word":"Minecraft Ideas","group_id":"3655333852768919885"},{"word":"The Walking Dead - Michonne Grimes","group_id":"6496547183752602150"},{"word":"China Manufacturers On TikTok","group_id":"4803523317665517023","word_type":"2"},{"word":"Asher And Ellie Full Story","group_id":"1809804295500205106","word_type":"2"},{"word":"Arsenal Vs Real Madrid Leg 2 Prediction","group_id":"330656041402269376","word_type":"2"},{"word":"Lv China Factory","group_id":"5484213058673903070"},{"word":"Legendary Loot Fridge Trend","group_id":"2793377218380266510"},{"word":"How To Solve A Rubiks Cube","group_id":"1366537867341468043"},{"word":"Louis Vuitton Respond To China","group_id":"7480375934997834797"}],"status_code":0,"status_msg":"","log_id":"202504171245278A585521E42ACC0E6900"}