{"data":[{"word":"capri new video","group_id":"4410889803088309743","word_type":"2"},{"word":"Halle Bailey Cctv Footage Of Ddg Reaction","group_id":"8042364758865655493","word_type":"2"},{"word":"California UFO Sighting 2025 In Evacuation","group_id":"8375970754299444231","word_type":"2"},{"word":"pipers new post","group_id":"4655736560681979799"},{"word":"Austin Mcbroom Side Of The Story","group_id":"948606686268462770"},{"word":"Black Woman Who Started The Ginger Trend","group_id":"7868244222471648426"},{"word":"Shameless - Veronica And Svetlana","group_id":"7711154103683609424"},{"word":"P Diddy Trial Update 2025 Footage","group_id":"7407993863623991719"},{"word":"The Good Part","group_id":"4710563486240405040"},{"word":"Shake It To The Max Billie Eilish","group_id":"7697792582983032609"}],"status_code":0,"status_msg":"","log_id":"202505190723171ED30DFBC6D50C073754"}