{"data":[{"word":"Zoey 101 Best Scenes","group_id":"6439190281303447361"},{"word":"TikTok Dance Trends","group_id":"4546372629618918720","word_type":"2"},{"word":"pokemon center restock","group_id":"5165032702800327202","word_type":"2"},{"word":"Diddy Verdict","group_id":"7445296880380789501","word_type":"2"},{"word":"Food Mukbangs","group_id":"150793515812860461"},{"word":"Food TikTok Recipes","group_id":"6984475858922535085"},{"word":"TikTok Asmr Videos","group_id":"1786955664005630619"},{"word":"What Does It Mean When Your Left Ear Rings","group_id":"4882489948627241258"},{"word":"Love Island Usa Ep 25","group_id":"5644202082945485025"},{"word":"I'm Not That Innocent Trend","group_id":"6064478818972223131"}],"status_code":0,"status_msg":"","log_id":"2025070118331685E2C24F1BF153079748"}