{"data":[{"word":"New Dance Trend 2025","group_id":"5798698427287332953","word_type":"2"},{"word":"Mr. Terrific Fight Scene","group_id":"191619104583033456","word_type":"2"},{"word":"Funny Baby Videos 2025","group_id":"5064369138905696373","word_type":"2"},{"word":"Latina Girl Effect Trend","group_id":"7856334687827331710"},{"word":"Huda On Call Her Daddy","group_id":"3700095126306677823"},{"word":"Back To School Haul","group_id":"3612699075266382966"},{"word":"‘The Summer I Turned Pretty’ Season 3","group_id":"3420676428504699029"},{"word":"Buckle Bunny King Kitty","group_id":"3478138653021894827"},{"word":"Gardening TikTok Trend","group_id":"211759107767498595"},{"word":"Berry Avenue Outfits","group_id":"5363325526874932456"}],"status_code":0,"status_msg":"","log_id":"20250717125245D96EB79A0FDB1F02392E"}