{"data":[{"word":"Machete - Walking Dead","group_id":"3884857718908737944"},{"word":"Dance TikTok 2025","group_id":"6045766266918963134","word_type":"2"},{"word":"Casey Anthony 2025","group_id":"2203362289823848741","word_type":"2"},{"word":"Iseop's Romance","group_id":"1335304778002835564","word_type":"2"},{"word":"Big B Update","group_id":"2034314623571582509"},{"word":"Al Green What Did He Say","group_id":"3921568441901000132"},{"word":"Timothee Dragging Kylie Out Of Oscars","group_id":"408914315288367696"},{"word":"A Day Before My Daughters Wedding","group_id":"7009197326605496220"},{"word":"Alvarez Goals","group_id":"2398027392619930211"},{"word":"Real Madrid Vs Atletico Madrid","group_id":"7184060032849254275"}],"status_code":0,"status_msg":"","log_id":"2025030518303332FEABF2E23D8D08EA35"}