{"data":[{"word":"TikTok Dances 2025","group_id":"7997607359311414522","word_type":"2"},{"word":"Funny Videos","group_id":"2073209185241970353","word_type":"2"},{"word":"Girlfriend TikTok Trend","group_id":"8953716221519189597","word_type":"2"},{"word":"Mukbangs Food","group_id":"2085021742158543003"},{"word":"2 People Dance Trend","group_id":"7763359630685340831"},{"word":"Cricut Ideas","group_id":"6408309330593113455"},{"word":"gf videos about her","group_id":"8441964010757369121"},{"word":"Down Below","group_id":"7335474958904993656"},{"word":"Delayed Voice","group_id":"5604139727320765852"},{"word":"Knitting Pattern Ideas","group_id":"3092297198702780826"}],"status_code":0,"status_msg":"","log_id":"20250706052339545A857746CD0961C806"}