{"data":[{"word":"Dance Trend 2025","group_id":"6520186081491815808","word_type":"2"},{"word":"Love Island USA Season 7 Winner","group_id":"6868596772282715237","word_type":"2"},{"word":"Diddy Reacting To His Prison Sentence","group_id":"3719324528493013335","word_type":"2"},{"word":"Songs To Lip Sync To Trend","group_id":"3957114303386309738"},{"word":"texas jigging bend trend","group_id":"4647223154387374434"},{"word":"Kitty Cat Trend","group_id":"3341989667900049800"},{"word":"new squirrel girl venom skin","group_id":"2824225904582968366"},{"word":"Skims Bra Review","group_id":"8523034164808544882"},{"word":"virus in grow a garden","group_id":"6763895965735900676"},{"word":"Milky Milk Milky Milk Trend","group_id":"6887830598083143753"}],"status_code":0,"status_msg":"","log_id":"20250714072743C47B6CC318E1F7017328"}