{"data":[{"word":"Dead Ocean Gameplay","group_id":"3153412058421469108","word_type":"2"},{"word":"Minecraft Cape","group_id":"8733724488717468229","word_type":"2"},{"word":"Skims Bra Review","group_id":"8523034164808544882"},{"word":"Trend TikTok In 2025","group_id":"219645876578616530","word_type":"2"},{"word":"Streaks Reminder","group_id":"435460299406810988"},{"word":"Kat Dennings At Jennifer Hudson","group_id":"175249595175417232"},{"word":"Live Minecraft","group_id":"7188346211763287021"},{"word":"Tbvnks Argue With His Girlfriend","group_id":"3135155727295860194"},{"word":"TikTok Dance Trend","group_id":"5896257190603099461"},{"word":"TikTok Trends With Friends","group_id":"6181533374256544165"}],"status_code":0,"status_msg":"","log_id":"20250325133044953693C74EF2DC063E0B"}